switchbot_cloud/__init__.py
switchbot_cloud/client.py
switchbot_cloud/devices.py
switchbot_cloud-0.2.5.dist-info/LICENSE
switchbot_cloud-0.2.5.dist-info/WHEEL
switchbot_cloud-0.2.5.dist-info/METADATA
switchbot_cloud-0.2.5.dist-info/RECORD
