Metadata-Version: 2.1
Name: switchbot-cloud
Version: 0.2.5
Summary: A Python API client for controlling SwitchBot devices via the SwitchBot Cloud API
License: MIT
Author: Eric Abruzzese
Author-email: eric.abruzzese@gmail.com
Requires-Python: >=3.6.2
Classifier: License :: OSI Approved :: MIT License
Classifier: Programming Language :: Python :: 3
Classifier: Programming Language :: Python :: 3.10
Classifier: Programming Language :: Python :: 3.7
Classifier: Programming Language :: Python :: 3.8
Classifier: Programming Language :: Python :: 3.9
Requires-Dist: pyhumps (>=3.0.2,<4.0.0)
Requires-Dist: requests (>=2.26.0,<3.0.0)
